csv2bq/__init__.py
csv2bq/csv2bq.py
csv2bq-0.1.2.dist-info/LICENSE
csv2bq-0.1.2.dist-info/METADATA
csv2bq-0.1.2.dist-info/WHEEL
csv2bq-0.1.2.dist-info/entry_points.txt
csv2bq-0.1.2.dist-info/top_level.txt
csv2bq-0.1.2.dist-info/RECORD
