Metadata-Version: 2.1
Name: csv2bq
Version: 0.1.2
Summary: upload local csv file to bigquery
Author: Hiroyuki Kuromiya
Author-email: 15026387+kromiii@users.noreply.github.com
License-File: LICENSE
Requires-Dist: google-cloud-bigquery
